{"nodes": [{"id": "home_deadmafia_documents_damascus_laundry_crates_dl_detect_src_graph_rs", "label": "graph.rs", "file_type": "code", "source_file": "crates/dl-detect/src/graph.rs", "source_location": "L1"}, {"id": "src_graph_tokenid", "label": "TokenId", "file_type": "code", "source_file": "crates/dl-detect/src/graph.rs", "source_location": "L64"}, {"id": "src_graph_edge", "label": "Edge", "file_type": "code", "source_file": "crates/dl-detect/src/graph.rs", "source_location": "L74"}, {"id": "pubkey", "label": "Pubkey", "file_type": "code", "source_file": "crates/dl-detect/src/graph.rs", "source_location": "L81"}, {"id": "ammkind", "label": "AmmKind", "file_type": "code", "source_file": "crates/dl-detect/src/graph.rs", "source_location": "L93"}, {"id": "src_graph_graph", "label": "Graph", "file_type": "code", "source_file": "crates/dl-detect/src/graph.rs", "source_location": "L99"}, {"id": "vec", "label": "Vec", "file_type": "code", "source_file": "crates/dl-detect/src/graph.rs", "source_location": "L101"}, {"id": "btreemap", "label": "BTreeMap", "file_type": "code", "source_file": "crates/dl-detect/src/graph.rs", "source_location": "L103"}, {"id": "src_graph_graph_new", "label": ".new()", "file_type": "code", "source_file": "crates/dl-detect/src/graph.rs", "source_location": "L113"}, {"id": "self", "label": "Self", "file_type": "code", "source_file": "crates/dl-detect/src/graph.rs", "source_location": "L113"}, {"id": "src_graph_graph_n_tokens", "label": ".n_tokens()", "file_type": "code", "source_file": "crates/dl-detect/src/graph.rs", "source_location": "L118"}, {"id": "src_graph_graph_n_edges", "label": ".n_edges()", "file_type": "code", "source_file": "crates/dl-detect/src/graph.rs", "source_location": "L123"}, {"id": "src_graph_graph_token_id", "label": ".token_id()", "file_type": "code", "source_file": "crates/dl-detect/src/graph.rs", "source_location": "L128"}, {"id": "option", "label": "Option", "file_type": "code", "source_file": "crates/dl-detect/src/graph.rs", "source_location": "L128"}, {"id": "src_graph_graph_intern_token", "label": ".intern_token()", "file_type": "code", "source_file": "crates/dl-detect/src/graph.rs", "source_location": "L134"}, {"id": "src_graph_graph_push_edge", "label": ".push_edge()", "file_type": "code", "source_file": "crates/dl-detect/src/graph.rs", "source_location": "L146"}, {"id": "src_graph_fee_multiplier_1e18", "label": "fee_multiplier_1e18()", "file_type": "code", "source_file": "crates/dl-detect/src/graph.rs", "source_location": "L154"}, {"id": "src_graph_effective_rate_1e18", "label": "effective_rate_1e18()", "file_type": "code", "source_file": "crates/dl-detect/src/graph.rs", "source_location": "L168"}, {"id": "result", "label": "Result", "file_type": "code", "source_file": "crates/dl-detect/src/graph.rs", "source_location": "L168"}, {"id": "detecterror", "label": "DetectError", "file_type": "code", "source_file": "crates/dl-detect/src/graph.rs", "source_location": "L168"}, {"id": "src_graph_weight_from_rate", "label": "weight_from_rate()", "file_type": "code", "source_file": "crates/dl-detect/src/graph.rs", "source_location": "L186"}, {"id": "src_graph_build_from_pools", "label": "build_from_pools()", "file_type": "code", "source_file": "crates/dl-detect/src/graph.rs", "source_location": "L210"}, {"id": "pool", "label": "Pool", "file_type": "code", "source_file": "crates/dl-detect/src/graph.rs", "source_location": "L210"}, {"id": "src_graph_sample_pool", "label": "sample_pool()", "file_type": "code", "source_file": "crates/dl-detect/src/graph.rs", "source_location": "L249"}, {"id": "src_graph_empty_pools_errors", "label": "empty_pools_errors()", "file_type": "code", "source_file": "crates/dl-detect/src/graph.rs", "source_location": "L266"}, {"id": "src_graph_single_pool_makes_two_edges", "label": "single_pool_makes_two_edges()", "file_type": "code", "source_file": "crates/dl-detect/src/graph.rs", "source_location": "L272"}, {"id": "src_graph_determinism_same_input_same_graph", "label": "determinism_same_input_same_graph()", "file_type": "code", "source_file": "crates/dl-detect/src/graph.rs", "source_location": "L286"}, {"id": "src_graph_two_pools_same_pair_make_4_edges", "label": "two_pools_same_pair_make_4_edges()", "file_type": "code", "source_file": "crates/dl-detect/src/graph.rs", "source_location": "L305"}, {"id": "src_graph_weight_positive_for_loss_leg", "label": "weight_positive_for_loss_leg()", "file_type": "code", "source_file": "crates/dl-detect/src/graph.rs", "source_location": "L360"}, {"id": "src_graph_weight_negative_for_profit_leg", "label": "weight_negative_for_profit_leg()", "file_type": "code", "source_file": "crates/dl-detect/src/graph.rs", "source_location": "L383"}, {"id": "src_graph_fee_reduces_magnitude_of_profit_leg_weight", "label": "fee_reduces_magnitude_of_profit_leg_weight()", "file_type": "code", "source_file": "crates/dl-detect/src/graph.rs", "source_location": "L397"}, {"id": "src_graph_zero_reserve_errors_with_div_by_zero", "label": "zero_reserve_errors_with_div_by_zero()", "file_type": "code", "source_file": "crates/dl-detect/src/graph.rs", "source_location": "L420"}, {"id": "src_graph_full_fee_pool_yields_max_loss_weights", "label": "full_fee_pool_yields_max_loss_weights()", "file_type": "code", "source_file": "crates/dl-detect/src/graph.rs", "source_location": "L433"}, {"id": "src_graph_multi_dex_triangle_dex_id_labeling", "label": "multi_dex_triangle_dex_id_labeling()", "file_type": "code", "source_file": "crates/dl-detect/src/graph.rs", "source_location": "L450"}], "edges": [{"source": "home_deadmafia_documents_damascus_laundry_crates_dl_detect_src_graph_rs", "target": "btreemap", "relation": "imports_from", "confidence": "EXTRACTED", "source_file": "crates/dl-detect/src/graph.rs", "source_location": "L48", "weight": 1.0, "context": "import"}, {"source": "home_deadmafia_documents_damascus_laundry_crates_dl_detect_src_graph_rs", "target": "mul_div_floor", "relation": "imports_from", "confidence": "EXTRACTED", "source_file": "crates/dl-detect/src/graph.rs", "source_location": "L50", "weight": 1.0, "context": "import"}, {"source": "home_deadmafia_documents_damascus_laundry_crates_dl_detect_src_graph_rs", "target": "ammkind", "relation": "imports_from", "confidence": "EXTRACTED", "source_file": "crates/dl-detect/src/graph.rs", "source_location": "L51", "weight": 1.0, "context": "import"}, {"source": "home_deadmafia_documents_damascus_laundry_crates_dl_detect_src_graph_rs", "target": "pool", "relation": "imports_from", "confidence": "EXTRACTED", "source_file": "crates/dl-detect/src/graph.rs", "source_location": "L52", "weight": 1.0, "context": "import"}, {"source": "home_deadmafia_documents_damascus_laundry_crates_dl_detect_src_graph_rs", "target": "detecterror", "relation": "imports_from", "confidence": "EXTRACTED", "source_file": "crates/dl-detect/src/graph.rs", "source_location": "L54", "weight": 1.0, "context": "import"}, {"source": "home_deadmafia_documents_damascus_laundry_crates_dl_detect_src_graph_rs", "target": "src_graph_tokenid", "relation": "contains", "confidence": "EXTRACTED", "source_file": "crates/dl-detect/src/graph.rs", "source_location": "L64", "weight": 1.0}, {"source": "home_deadmafia_documents_damascus_laundry_crates_dl_detect_src_graph_rs", "target": "src_graph_edge", "relation": "contains", "confidence": "EXTRACTED", "source_file": "crates/dl-detect/src/graph.rs", "source_location": "L74", "weight": 1.0}, {"source": "src_graph_edge", "target": "src_graph_tokenid", "relation": "references", "confidence": "EXTRACTED", "source_file": "crates/dl-detect/src/graph.rs", "source_location": "L75", "weight": 1.0, "context": "field"}, {"source": "src_graph_edge", "target": "src_graph_tokenid", "relation": "references", "confidence": "EXTRACTED", "source_file": "crates/dl-detect/src/graph.rs", "source_location": "L76", "weight": 1.0, "context": "field"}, {"source": "src_graph_edge", "target": "pubkey", "relation": "references", "confidence": "EXTRACTED", "source_file": "crates/dl-detect/src/graph.rs", "source_location": "L81", "weight": 1.0, "context": "field"}, {"source": "src_graph_edge", "target": "ammkind", "relation": "references", "confidence": "EXTRACTED", "source_file": "crates/dl-detect/src/graph.rs", "source_location": "L93", "weight": 1.0, "context": "field"}, {"source": "home_deadmafia_documents_damascus_laundry_crates_dl_detect_src_graph_rs", "target": "src_graph_graph", "relation": "contains", "confidence": "EXTRACTED", "source_file": "crates/dl-detect/src/graph.rs", "source_location": "L99", "weight": 1.0}, {"source": "src_graph_graph", "target": "vec", "relation": "references", "confidence": "EXTRACTED", "source_file": "crates/dl-detect/src/graph.rs", "source_location": "L101", "weight": 1.0, "context": "field"}, {"source": "src_graph_graph", "target": "pubkey", "relation": "references", "confidence": "EXTRACTED", "source_file": "crates/dl-detect/src/graph.rs", "source_location": "L101", "weight": 1.0, "context": "generic_arg"}, {"source": "src_graph_graph", "target": "btreemap", "relation": "references", "confidence": "EXTRACTED", "source_file": "crates/dl-detect/src/graph.rs", "source_location": "L103", "weight": 1.0, "context": "field"}, {"source": "src_graph_graph", "target": "src_graph_tokenid", "relation": "references", "confidence": "EXTRACTED", "source_file": "crates/dl-detect/src/graph.rs", "source_location": "L103", "weight": 1.0, "context": "generic_arg"}, {"source": "src_graph_graph", "target": "vec", "relation": "references", "confidence": "EXTRACTED", "source_file": "crates/dl-detect/src/graph.rs", "source_location": "L107", "weight": 1.0, "context": "field"}, {"source": "src_graph_graph", "target": "src_graph_edge", "relation": "references", "confidence": "EXTRACTED", "source_file": "crates/dl-detect/src/graph.rs", "source_location": "L107", "weight": 1.0, "context": "generic_arg"}, {"source": "src_graph_graph", "target": "src_graph_graph_new", "relation": "method", "confidence": "EXTRACTED", "source_file": "crates/dl-detect/src/graph.rs", "source_location": "L113", "weight": 1.0}, {"source": "src_graph_graph_new", "target": "self", "relation": "references", "confidence": "EXTRACTED", "source_file": "crates/dl-detect/src/graph.rs", "source_location": "L113", "weight": 1.0, "context": "return_type"}, {"source": "src_graph_graph", "target": "src_graph_graph_n_tokens", "relation": "method", "confidence": "EXTRACTED", "source_file": "crates/dl-detect/src/graph.rs", "source_location": "L118", "weight": 1.0}, {"source": "src_graph_graph", "target": "src_graph_graph_n_edges", "relation": "method", "confidence": "EXTRACTED", "source_file": "crates/dl-detect/src/graph.rs", "source_location": "L123", "weight": 1.0}, {"source": "src_graph_graph", "target": "src_graph_graph_token_id", "relation": "method", "confidence": "EXTRACTED", "source_file": "crates/dl-detect/src/graph.rs", "source_location": "L128", "weight": 1.0}, {"source": "src_graph_graph_token_id", "target": "option", "relation": "references", "confidence": "EXTRACTED", "source_file": "crates/dl-detect/src/graph.rs", "source_location": "L128", "weight": 1.0, "context": "return_type"}, {"source": "src_graph_graph_token_id", "target": "src_graph_tokenid", "relation": "references", "confidence": "EXTRACTED", "source_file": "crates/dl-detect/src/graph.rs", "source_location": "L128", "weight": 1.0, "context": "generic_arg"}, {"source": "src_graph_graph", "target": "src_graph_graph_intern_token", "relation": "method", "confidence": "EXTRACTED", "source_file": "crates/dl-detect/src/graph.rs", "source_location": "L134", "weight": 1.0}, {"source": "src_graph_graph_intern_token", "target": "pubkey", "relation": "references", "confidence": "EXTRACTED", "source_file": "crates/dl-detect/src/graph.rs", "source_location": "L134", "weight": 1.0, "context": "parameter_type"}, {"source": "src_graph_graph_intern_token", "target": "src_graph_tokenid", "relation": "references", "confidence": "EXTRACTED", "source_file": "crates/dl-detect/src/graph.rs", "source_location": "L134", "weight": 1.0, "context": "return_type"}, {"source": "src_graph_graph", "target": "src_graph_graph_push_edge", "relation": "method", "confidence": "EXTRACTED", "source_file": "crates/dl-detect/src/graph.rs", "source_location": "L146", "weight": 1.0}, {"source": "src_graph_graph_push_edge", "target": "src_graph_edge", "relation": "references", "confidence": "EXTRACTED", "source_file": "crates/dl-detect/src/graph.rs", "source_location": "L146", "weight": 1.0, "context": "parameter_type"}, {"source": "home_deadmafia_documents_damascus_laundry_crates_dl_detect_src_graph_rs", "target": "src_graph_fee_multiplier_1e18", "relation": "contains", "confidence": "EXTRACTED", "source_file": "crates/dl-detect/src/graph.rs", "source_location": "L154", "weight": 1.0}, {"source": "home_deadmafia_documents_damascus_laundry_crates_dl_detect_src_graph_rs", "target": "src_graph_effective_rate_1e18", "relation": "contains", "confidence": "EXTRACTED", "source_file": "crates/dl-detect/src/graph.rs", "source_location": "L168", "weight": 1.0}, {"source": "src_graph_effective_rate_1e18", "target": "result", "relation": "references", "confidence": "EXTRACTED", "source_file": "crates/dl-detect/src/graph.rs", "source_location": "L168", "weight": 1.0, "context": "return_type"}, {"source": "src_graph_effective_rate_1e18", "target": "detecterror", "relation": "references", "confidence": "EXTRACTED", "source_file": "crates/dl-detect/src/graph.rs", "source_location": "L168", "weight": 1.0, "context": "generic_arg"}, {"source": "home_deadmafia_documents_damascus_laundry_crates_dl_detect_src_graph_rs", "target": "src_graph_weight_from_rate", "relation": "contains", "confidence": "EXTRACTED", "source_file": "crates/dl-detect/src/graph.rs", "source_location": "L186", "weight": 1.0}, {"source": "home_deadmafia_documents_damascus_laundry_crates_dl_detect_src_graph_rs", "target": "src_graph_build_from_pools", "relation": "contains", "confidence": "EXTRACTED", "source_file": "crates/dl-detect/src/graph.rs", "source_location": "L210", "weight": 1.0}, {"source": "src_graph_build_from_pools", "target": "pool", "relation": "references", "confidence": "EXTRACTED", "source_file": "crates/dl-detect/src/graph.rs", "source_location": "L210", "weight": 1.0, "context": "parameter_type"}, {"source": "src_graph_build_from_pools", "target": "result", "relation": "references", "confidence": "EXTRACTED", "source_file": "crates/dl-detect/src/graph.rs", "source_location": "L210", "weight": 1.0, "context": "return_type"}, {"source": "src_graph_build_from_pools", "target": "src_graph_graph", "relation": "references", "confidence": "EXTRACTED", "source_file": "crates/dl-detect/src/graph.rs", "source_location": "L210", "weight": 1.0, "context": "generic_arg"}, {"source": "src_graph_build_from_pools", "target": "detecterror", "relation": "references", "confidence": "EXTRACTED", "source_file": "crates/dl-detect/src/graph.rs", "source_location": "L210", "weight": 1.0, "context": "generic_arg"}, {"source": "home_deadmafia_documents_damascus_laundry_crates_dl_detect_src_graph_rs", "target": "super", "relation": "imports_from", "confidence": "EXTRACTED", "source_file": "crates/dl-detect/src/graph.rs", "source_location": "L246", "weight": 1.0, "context": "import"}, {"source": "home_deadmafia_documents_damascus_laundry_crates_dl_detect_src_graph_rs", "target": "dl_state", "relation": "imports_from", "confidence": "EXTRACTED", "source_file": "crates/dl-detect/src/graph.rs", "source_location": "L247", "weight": 1.0, "context": "import"}, {"source": "home_deadmafia_documents_damascus_laundry_crates_dl_detect_src_graph_rs", "target": "src_graph_sample_pool", "relation": "contains", "confidence": "EXTRACTED", "source_file": "crates/dl-detect/src/graph.rs", "source_location": "L249", "weight": 1.0}, {"source": "src_graph_sample_pool", "target": "pool", "relation": "references", "confidence": "EXTRACTED", "source_file": "crates/dl-detect/src/graph.rs", "source_location": "L249", "weight": 1.0, "context": "return_type"}, {"source": "home_deadmafia_documents_damascus_laundry_crates_dl_detect_src_graph_rs", "target": "src_graph_empty_pools_errors", "relation": "contains", "confidence": "EXTRACTED", "source_file": "crates/dl-detect/src/graph.rs", "source_location": "L266", "weight": 1.0}, {"source": "home_deadmafia_documents_damascus_laundry_crates_dl_detect_src_graph_rs", "target": "src_graph_single_pool_makes_two_edges", "relation": "contains", "confidence": "EXTRACTED", "source_file": "crates/dl-detect/src/graph.rs", "source_location": "L272", "weight": 1.0}, {"source": "home_deadmafia_documents_damascus_laundry_crates_dl_detect_src_graph_rs", "target": "src_graph_determinism_same_input_same_graph", "relation": "contains", "confidence": "EXTRACTED", "source_file": "crates/dl-detect/src/graph.rs", "source_location": "L286", "weight": 1.0}, {"source": "home_deadmafia_documents_damascus_laundry_crates_dl_detect_src_graph_rs", "target": "src_graph_two_pools_same_pair_make_4_edges", "relation": "contains", "confidence": "EXTRACTED", "source_file": "crates/dl-detect/src/graph.rs", "source_location": "L305", "weight": 1.0}, {"source": "home_deadmafia_documents_damascus_laundry_crates_dl_detect_src_graph_rs", "target": "src_graph_weight_positive_for_loss_leg", "relation": "contains", "confidence": "EXTRACTED", "source_file": "crates/dl-detect/src/graph.rs", "source_location": "L360", "weight": 1.0}, {"source": "home_deadmafia_documents_damascus_laundry_crates_dl_detect_src_graph_rs", "target": "src_graph_weight_negative_for_profit_leg", "relation": "contains", "confidence": "EXTRACTED", "source_file": "crates/dl-detect/src/graph.rs", "source_location": "L383", "weight": 1.0}, {"source": "home_deadmafia_documents_damascus_laundry_crates_dl_detect_src_graph_rs", "target": "src_graph_fee_reduces_magnitude_of_profit_leg_weight", "relation": "contains", "confidence": "EXTRACTED", "source_file": "crates/dl-detect/src/graph.rs", "source_location": "L397", "weight": 1.0}, {"source": "home_deadmafia_documents_damascus_laundry_crates_dl_detect_src_graph_rs", "target": "src_graph_zero_reserve_errors_with_div_by_zero", "relation": "contains", "confidence": "EXTRACTED", "source_file": "crates/dl-detect/src/graph.rs", "source_location": "L420", "weight": 1.0}, {"source": "home_deadmafia_documents_damascus_laundry_crates_dl_detect_src_graph_rs", "target": "src_graph_full_fee_pool_yields_max_loss_weights", "relation": "contains", "confidence": "EXTRACTED", "source_file": "crates/dl-detect/src/graph.rs", "source_location": "L433", "weight": 1.0}, {"source": "home_deadmafia_documents_damascus_laundry_crates_dl_detect_src_graph_rs", "target": "src_graph_multi_dex_triangle_dex_id_labeling", "relation": "contains", "confidence": "EXTRACTED", "source_file": "crates/dl-detect/src/graph.rs", "source_location": "L450", "weight": 1.0}, {"source": "src_graph_graph_intern_token", "target": "src_graph_tokenid", "relation": "calls", "context": "call", "confidence": "EXTRACTED", "source_file": "crates/dl-detect/src/graph.rs", "source_location": "L138", "weight": 1.0}, {"source": "src_graph_build_from_pools", "target": "src_graph_graph_new", "relation": "calls", "context": "call", "confidence": "EXTRACTED", "source_file": "crates/dl-detect/src/graph.rs", "source_location": "L215", "weight": 1.0}, {"source": "src_graph_build_from_pools", "target": "src_graph_graph_intern_token", "relation": "calls", "context": "call", "confidence": "EXTRACTED", "source_file": "crates/dl-detect/src/graph.rs", "source_location": "L217", "weight": 1.0}, {"source": "src_graph_build_from_pools", "target": "src_graph_fee_multiplier_1e18", "relation": "calls", "context": "call", "confidence": "EXTRACTED", "source_file": "crates/dl-detect/src/graph.rs", "source_location": "L219", "weight": 1.0}, {"source": "src_graph_build_from_pools", "target": "src_graph_effective_rate_1e18", "relation": "calls", "context": "call", "confidence": "EXTRACTED", "source_file": "crates/dl-detect/src/graph.rs", "source_location": "L221", "weight": 1.0}, {"source": "src_graph_build_from_pools", "target": "src_graph_graph_push_edge", "relation": "calls", "context": "call", "confidence": "EXTRACTED", "source_file": "crates/dl-detect/src/graph.rs", "source_location": "L224", "weight": 1.0}, {"source": "src_graph_build_from_pools", "target": "src_graph_weight_from_rate", "relation": "calls", "context": "call", "confidence": "EXTRACTED", "source_file": "crates/dl-detect/src/graph.rs", "source_location": "L227", "weight": 1.0}, {"source": "src_graph_sample_pool", "target": "pubkey", "relation": "calls", "context": "call", "confidence": "EXTRACTED", "source_file": "crates/dl-detect/src/graph.rs", "source_location": "L251", "weight": 1.0}, {"source": "src_graph_empty_pools_errors", "target": "src_graph_build_from_pools", "relation": "calls", "context": "call", "confidence": "EXTRACTED", "source_file": "crates/dl-detect/src/graph.rs", "source_location": "L267", "weight": 1.0}, {"source": "src_graph_single_pool_makes_two_edges", "target": "src_graph_sample_pool", "relation": "calls", "context": "call", "confidence": "EXTRACTED", "source_file": "crates/dl-detect/src/graph.rs", "source_location": "L273", "weight": 1.0}, {"source": "src_graph_single_pool_makes_two_edges", "target": "src_graph_build_from_pools", "relation": "calls", "context": "call", "confidence": "EXTRACTED", "source_file": "crates/dl-detect/src/graph.rs", "source_location": "L274", "weight": 1.0}, {"source": "src_graph_single_pool_makes_two_edges", "target": "src_graph_graph_token_id", "relation": "calls", "context": "call", "confidence": "EXTRACTED", "source_file": "crates/dl-detect/src/graph.rs", "source_location": "L277", "weight": 1.0}, {"source": "src_graph_determinism_same_input_same_graph", "target": "src_graph_build_from_pools", "relation": "calls", "context": "call", "confidence": "EXTRACTED", "source_file": "crates/dl-detect/src/graph.rs", "source_location": "L291", "weight": 1.0}, {"source": "src_graph_two_pools_same_pair_make_4_edges", "target": "src_graph_build_from_pools", "relation": "calls", "context": "call", "confidence": "EXTRACTED", "source_file": "crates/dl-detect/src/graph.rs", "source_location": "L310", "weight": 1.0}, {"source": "src_graph_two_pools_same_pair_make_4_edges", "target": "src_graph_graph_token_id", "relation": "calls", "context": "call", "confidence": "EXTRACTED", "source_file": "crates/dl-detect/src/graph.rs", "source_location": "L316", "weight": 1.0}, {"source": "src_graph_two_pools_same_pair_make_4_edges", "target": "src_graph_graph_new", "relation": "calls", "context": "call", "confidence": "EXTRACTED", "source_file": "crates/dl-detect/src/graph.rs", "source_location": "L334", "weight": 1.0}, {"source": "src_graph_weight_positive_for_loss_leg", "target": "src_graph_sample_pool", "relation": "calls", "context": "call", "confidence": "EXTRACTED", "source_file": "crates/dl-detect/src/graph.rs", "source_location": "L363", "weight": 1.0}, {"source": "src_graph_weight_positive_for_loss_leg", "target": "src_graph_build_from_pools", "relation": "calls", "context": "call", "confidence": "EXTRACTED", "source_file": "crates/dl-detect/src/graph.rs", "source_location": "L364", "weight": 1.0}, {"source": "src_graph_weight_negative_for_profit_leg", "target": "src_graph_sample_pool", "relation": "calls", "context": "call", "confidence": "EXTRACTED", "source_file": "crates/dl-detect/src/graph.rs", "source_location": "L384", "weight": 1.0}, {"source": "src_graph_weight_negative_for_profit_leg", "target": "src_graph_build_from_pools", "relation": "calls", "context": "call", "confidence": "EXTRACTED", "source_file": "crates/dl-detect/src/graph.rs", "source_location": "L385", "weight": 1.0}, {"source": "src_graph_fee_reduces_magnitude_of_profit_leg_weight", "target": "src_graph_build_from_pools", "relation": "calls", "context": "call", "confidence": "EXTRACTED", "source_file": "crates/dl-detect/src/graph.rs", "source_location": "L401", "weight": 1.0}, {"source": "src_graph_fee_reduces_magnitude_of_profit_leg_weight", "target": "src_graph_sample_pool", "relation": "calls", "context": "call", "confidence": "EXTRACTED", "source_file": "crates/dl-detect/src/graph.rs", "source_location": "L401", "weight": 1.0}, {"source": "src_graph_zero_reserve_errors_with_div_by_zero", "target": "src_graph_sample_pool", "relation": "calls", "context": "call", "confidence": "EXTRACTED", "source_file": "crates/dl-detect/src/graph.rs", "source_location": "L421", "weight": 1.0}, {"source": "src_graph_zero_reserve_errors_with_div_by_zero", "target": "src_graph_build_from_pools", "relation": "calls", "context": "call", "confidence": "EXTRACTED", "source_file": "crates/dl-detect/src/graph.rs", "source_location": "L422", "weight": 1.0}, {"source": "src_graph_full_fee_pool_yields_max_loss_weights", "target": "src_graph_sample_pool", "relation": "calls", "context": "call", "confidence": "EXTRACTED", "source_file": "crates/dl-detect/src/graph.rs", "source_location": "L434", "weight": 1.0}, {"source": "src_graph_full_fee_pool_yields_max_loss_weights", "target": "src_graph_build_from_pools", "relation": "calls", "context": "call", "confidence": "EXTRACTED", "source_file": "crates/dl-detect/src/graph.rs", "source_location": "L435", "weight": 1.0}, {"source": "src_graph_multi_dex_triangle_dex_id_labeling", "target": "pubkey", "relation": "calls", "context": "call", "confidence": "EXTRACTED", "source_file": "crates/dl-detect/src/graph.rs", "source_location": "L456", "weight": 1.0}, {"source": "src_graph_multi_dex_triangle_dex_id_labeling", "target": "src_graph_build_from_pools", "relation": "calls", "context": "call", "confidence": "EXTRACTED", "source_file": "crates/dl-detect/src/graph.rs", "source_location": "L500", "weight": 1.0}, {"source": "src_graph_multi_dex_triangle_dex_id_labeling", "target": "src_graph_graph_new", "relation": "calls", "context": "call", "confidence": "EXTRACTED", "source_file": "crates/dl-detect/src/graph.rs", "source_location": "L502", "weight": 1.0}], "raw_calls": [{"caller_nid": "src_graph_graph_token_id", "callee": "copied", "is_member_call": true, "source_file": "/home/deadmafia/Documents/damascus_laundry/crates/dl-detect/src/graph.rs", "source_location": "L129"}, {"caller_nid": "src_graph_graph_intern_token", "callee": "as_ref", "is_member_call": true, "source_file": "/home/deadmafia/Documents/damascus_laundry/crates/dl-detect/src/graph.rs", "source_location": "L135"}, {"caller_nid": "src_graph_fee_multiplier_1e18", "callee": "saturating_mul", "is_member_call": true, "source_file": "/home/deadmafia/Documents/damascus_laundry/crates/dl-detect/src/graph.rs", "source_location": "L157"}, {"caller_nid": "src_graph_fee_multiplier_1e18", "callee": "saturating_sub", "is_member_call": true, "source_file": "/home/deadmafia/Documents/damascus_laundry/crates/dl-detect/src/graph.rs", "source_location": "L158"}, {"caller_nid": "src_graph_effective_rate_1e18", "callee": "mul_div_floor", "is_member_call": false, "source_file": "/home/deadmafia/Documents/damascus_laundry/crates/dl-detect/src/graph.rs", "source_location": "L178"}, {"caller_nid": "src_graph_effective_rate_1e18", "callee": "mul_div_floor", "is_member_call": false, "source_file": "/home/deadmafia/Documents/damascus_laundry/crates/dl-detect/src/graph.rs", "source_location": "L180"}, {"caller_nid": "src_graph_weight_from_rate", "callee": "clamp", "is_member_call": true, "source_file": "/home/deadmafia/Documents/damascus_laundry/crates/dl-detect/src/graph.rs", "source_location": "L188"}, {"caller_nid": "src_graph_two_pools_same_pair_make_4_edges", "callee": "sort", "is_member_call": true, "source_file": "/home/deadmafia/Documents/damascus_laundry/crates/dl-detect/src/graph.rs", "source_location": "L333"}, {"caller_nid": "src_graph_two_pools_same_pair_make_4_edges", "callee": "or_insert", "is_member_call": true, "source_file": "/home/deadmafia/Documents/damascus_laundry/crates/dl-detect/src/graph.rs", "source_location": "L336"}, {"caller_nid": "src_graph_two_pools_same_pair_make_4_edges", "callee": "entry", "is_member_call": true, "source_file": "/home/deadmafia/Documents/damascus_laundry/crates/dl-detect/src/graph.rs", "source_location": "L336"}, {"caller_nid": "src_graph_two_pools_same_pair_make_4_edges", "callee": "into_iter", "is_member_call": true, "source_file": "/home/deadmafia/Documents/damascus_laundry/crates/dl-detect/src/graph.rs", "source_location": "L338"}, {"caller_nid": "src_graph_two_pools_same_pair_make_4_edges", "callee": "sort_by_key", "is_member_call": true, "source_file": "/home/deadmafia/Documents/damascus_laundry/crates/dl-detect/src/graph.rs", "source_location": "L350"}, {"caller_nid": "src_graph_two_pools_same_pair_make_4_edges", "callee": "dedup", "is_member_call": true, "source_file": "/home/deadmafia/Documents/damascus_laundry/crates/dl-detect/src/graph.rs", "source_location": "L351"}]}